{
    "settings": {
        "nshots": 2048,
        "relaxation_time": 100000
    },
    "configs": {
        "qm/bounds": {
            "kind": "bounds",
            "waveforms": 40000.0,
            "readout": 30,
            "instructions": 1000000
        },
        "twpaB": {
            "kind": "oscillator",
            "frequency": 6488000000.0,
            "power": -2.75
        },
        "twpaD": {
            "kind": "oscillator",
            "frequency": 6149000000.0,
            "power": -2.6
        },
        "A1/drive": {
            "kind": "iq",
            "frequency": 4900000000.0
        },
        "A1/drive12": {
            "kind": "iq",
            "frequency": 4900000000.0
        },
        "A1/probe": {
            "kind": "iq",
            "frequency": 7134250000.0
        },
        "A2/drive": {
            "kind": "iq",
            "frequency": 5700000000.0
        },
        "A2/drive12": {
            "kind": "iq",
            "frequency": 5700000000.0
        },
        "A2/probe": {
            "kind": "iq",
            "frequency": 7400400000.0
        },
        "A3/drive": {
            "kind": "iq",
            "frequency": 5700000000.0
        },
        "A3/drive12": {
            "kind": "iq",
            "frequency": 5700000000.0
        },
        "A3/probe": {
            "kind": "iq",
            "frequency": 7490250000.0
        },
        "A4/drive": {
            "kind": "iq",
            "frequency": 4900000000.0
        },
        "A4/drive12": {
            "kind": "iq",
            "frequency": 4900000000.0
        },
        "A4/probe": {
            "kind": "iq",
            "frequency": 7242800000.0
        },
        "A5/drive": {
            "kind": "iq",
            "frequency": 5700000000.0
        },
        "A5/drive12": {
            "kind": "iq",
            "frequency": 5700000000.0
        },
        "A5/probe": {
            "kind": "iq",
            "frequency": 7640000000.0
        },
        "A6/drive": {
            "kind": "iq",
            "frequency": 6500000000.0
        },
        "A6/drive12": {
            "kind": "iq",
            "frequency": 6500000000.0
        },
        "A6/probe": {
            "kind": "iq",
            "frequency": 7742200000.0
        },
        "B1/drive": {
            "kind": "iq",
            "frequency": 5000388701.0
        },
        "B1/drive12": {
            "kind": "iq",
            "frequency": 4900000000.0
        },
        "B1/probe": {
            "kind": "iq",
            "frequency": 7132548764.0
        },
        "B2/drive": {
            "kind": "iq",
            "frequency": 5963761228.0
        },
        "B2/drive12": {
            "kind": "iq",
            "frequency": 5766856000.0
        },
        "B2/probe": {
            "kind": "iq",
            "frequency": 7380040944.0
        },
        "B3/drive": {
            "kind": "iq",
            "frequency": 5684623790.0
        },
        "B3/drive12": {
            "kind": "iq",
            "frequency": 5468650012.0
        },
        "B3/probe": {
            "kind": "iq",
            "frequency": 7480622376.0
        },
        "B4/drive": {
            "kind": "iq",
            "frequency": 6809615374.0
        },
        "B4/drive12": {
            "kind": "iq",
            "frequency": 6612097382.0
        },
        "B4/probe": {
            "kind": "iq",
            "frequency": 7700300527.0
        },
        "B5/drive": {
            "kind": "iq",
            "frequency": 5742046323.0
        },
        "B5/drive12": {
            "kind": "iq",
            "frequency": 5700000000.0
        },
        "B5/probe": {
            "kind": "iq",
            "frequency": 7640679567.0
        },
        "D1/drive": {
            "kind": "iq",
            "frequency": 4959156389.0
        },
        "D1/drive12": {
            "kind": "iq",
            "frequency": 4748442235.0
        },
        "D1/probe": {
            "kind": "iq",
            "frequency": 7129689869.0
        },
        "D2/drive": {
            "kind": "iq",
            "frequency": 5568088582.0
        },
        "D2/drive12": {
            "kind": "iq",
            "frequency": 5354064200.0
        },
        "D2/probe": {
            "kind": "iq",
            "frequency": 7369114653.0
        },
        "D3/drive": {
            "kind": "iq",
            "frequency": 5657525186.0
        },
        "D3/drive12": {
            "kind": "iq",
            "frequency": 5700000000.0
        },
        "D3/probe": {
            "kind": "iq",
            "frequency": 7477730627.0
        },
        "D4/drive": {
            "kind": "iq",
            "frequency": 6248620764.0
        },
        "D4/drive12": {
            "kind": "iq",
            "frequency": 6500000000.0
        },
        "D4/probe": {
            "kind": "iq",
            "frequency": 7692937024.0
        },
        "D5/drive": {
            "kind": "iq",
            "frequency": 5532340384.0
        },
        "D5/drive12": {
            "kind": "iq",
            "frequency": 5700000000.0
        },
        "D5/probe": {
            "kind": "iq",
            "frequency": 7628420035.0
        },
        "A1/acquisition": {
            "kind": "qm-acquisition",
            "delay": 224.0,
            "smearing": 0.0,
            "threshold": 0.0,
            "iq_angle": 0.0,
            "kernel": null,
            "gain": 0,
            "offset": 0.0
        },
        "A2/acquisition": {
            "kind": "qm-acquisition",
            "delay": 224.0,
            "smearing": 0.0,
            "threshold": 0.0,
            "iq_angle": 0.0,
            "kernel": null,
            "gain": 0,
            "offset": 0.0
        },
        "A3/acquisition": {
            "kind": "qm-acquisition",
            "delay": 224.0,
            "smearing": 0.0,
            "threshold": 0.0,
            "iq_angle": 0.0,
            "kernel": null,
            "gain": 0,
            "offset": 0.0
        },
        "A4/acquisition": {
            "kind": "qm-acquisition",
            "delay": 224.0,
            "smearing": 0.0,
            "threshold": 0.0,
            "iq_angle": 0.0,
            "kernel": null,
            "gain": 0,
            "offset": 0.0
        },
        "A5/acquisition": {
            "kind": "qm-acquisition",
            "delay": 224.0,
            "smearing": 0.0,
            "threshold": 0.0,
            "iq_angle": 0.0,
            "kernel": null,
            "gain": 0,
            "offset": 0.0
        },
        "A6/acquisition": {
            "kind": "qm-acquisition",
            "delay": 224.0,
            "smearing": 0.0,
            "threshold": 0.0,
            "iq_angle": 0.0,
            "kernel": null,
            "gain": 0,
            "offset": 0.0
        },
        "B1/acquisition": {
            "kind": "qm-acquisition",
            "delay": 224.0,
            "smearing": 0.0,
            "threshold": 0.0008494611165541193,
            "iq_angle": -0.0043567794003432124,
            "kernel": null,
            "gain": 10,
            "offset": 0.0
        },
        "B2/acquisition": {
            "kind": "qm-acquisition",
            "delay": 224.0,
            "smearing": 0.0,
            "threshold": 0.002499868004267324,
            "iq_angle": 0.6722312664314924,
            "kernel": null,
            "gain": 10,
            "offset": 0.0
        },
        "B3/acquisition": {
            "kind": "qm-acquisition",
            "delay": 224.0,
            "smearing": 0.0,
            "threshold": 0.0026927888724794886,
            "iq_angle": -2.6615127227279918,
            "kernel": null,
            "gain": 10,
            "offset": 0.0
        },
        "B4/acquisition": {
            "kind": "qm-acquisition",
            "delay": 224.0,
            "smearing": 0.0,
            "threshold": -0.0005571645574693968,
            "iq_angle": 0.988586127592961,
            "kernel": null,
            "gain": 10,
            "offset": 0.0
        },
        "B5/acquisition": {
            "kind": "qm-acquisition",
            "delay": 224.0,
            "smearing": 0.0,
            "threshold": 0.0010562843616691592,
            "iq_angle": -0.2956293899760952,
            "kernel": null,
            "gain": 10,
            "offset": 0.0
        },
        "D1/acquisition": {
            "kind": "qm-acquisition",
            "delay": 224.0,
            "smearing": 0.0,
            "threshold": 0.001952998167648245,
            "iq_angle": -0.8030878198565996,
            "kernel": null,
            "gain": 10,
            "offset": 0.0
        },
        "D2/acquisition": {
            "kind": "qm-acquisition",
            "delay": 224.0,
            "smearing": 0.0,
            "threshold": 0.0034645063414544194,
            "iq_angle": -1.3959502833839366,
            "kernel": null,
            "gain": 10,
            "offset": 0.0
        },
        "D3/acquisition": {
            "kind": "qm-acquisition",
            "delay": 224.0,
            "smearing": 0.0,
            "threshold": 0.0022424279381051404,
            "iq_angle": -0.6451888951164113,
            "kernel": null,
            "gain": 10,
            "offset": 0.0
        },
        "D4/acquisition": {
            "kind": "qm-acquisition",
            "delay": 224.0,
            "smearing": 0.0,
            "threshold": 0.0020330453601376305,
            "iq_angle": -2.426283659399824,
            "kernel": null,
            "gain": 10,
            "offset": 0.0
        },
        "D5/acquisition": {
            "kind": "qm-acquisition",
            "delay": 224.0,
            "smearing": 0.0,
            "threshold": 0.0030892145059463814,
            "iq_angle": -2.893234172069562,
            "kernel": null,
            "gain": 10,
            "offset": 0.0
        },
        "A1/flux": {
            "kind": "opx-output",
            "offset": 0.0,
            "filter": {},
            "output_mode": "direct"
        },
        "A2/flux": {
            "kind": "opx-output",
            "offset": 0.0,
            "filter": {},
            "output_mode": "direct"
        },
        "A3/flux": {
            "kind": "opx-output",
            "offset": 0.0,
            "filter": {},
            "output_mode": "direct"
        },
        "A4/flux": {
            "kind": "opx-output",
            "offset": 0.0,
            "filter": {},
            "output_mode": "direct"
        },
        "A5/flux": {
            "kind": "opx-output",
            "offset": 0.0,
            "filter": {},
            "output_mode": "direct"
        },
        "A6/flux": {
            "kind": "opx-output",
            "offset": 0.0,
            "filter": {},
            "output_mode": "direct"
        },
        "B1/flux": {
            "kind": "opx-output",
            "offset": -0.25498290735703955,
            "filter": {
                "feedforward": [
                    1.0732356581468765,
                    -0.9791199412206626,
                    -0.0004547559775228452,
                    -0.0004504045023570667,
                    -0.003051036583314867,
                    -0.001074854121775941,
                    -0.004607678438759177,
                    0.002385541630165718,
                    -0.0017138910938667429,
                    0.0006148219537056932,
                    0.005923316318663047,
                    0.010006220587642417,
                    0.001438086105103124,
                    -0.004341564296401992,
                    0.004175732130486821,
                    -0.005614498228393307,
                    -0.0011315093271103778,
                    -0.01024543105861858,
                    0.010018434002976766,
                    -0.014970843971975093,
                    0.0117942029038862
                ],
                "feedback": [
                    0.9999990463256836,
                    0.9071785948809611
                ]
            },
            "output_mode": "direct"
        },
        "B2/flux": {
            "kind": "opx-output",
            "offset": 0.10729465913983083,
            "filter": {
                "feedforward": [
                    1.0885500560613104,
                    -1.0204832803900936,
                    -0.0006862238683308141,
                    -0.0006731619494092199,
                    0.008683454263293127,
                    0.005511507962538395,
                    -0.0007216745406470205,
                    0.002800284628697953,
                    -0.013301029465135956,
                    -0.007834116032701465,
                    0.00940678877778317,
                    0.005378611284490081,
                    0.006279309320693283,
                    -0.005221574830971296,
                    -0.001929305884062559,
                    -0.00020173147048744173,
                    -0.003733834854073862,
                    0.007462222810813454,
                    -0.0027190379797511774,
                    -0.005289307628951209,
                    0.003801188870972671
                ],
                "feedback": [
                    0.9999990463256836,
                    0.9249288239267979
                ]
            },
            "output_mode": "direct"
        },
        "B3/flux": {
            "kind": "opx-output",
            "offset": 0.2226188560782865,
            "filter": {
                "feedforward": [
                    1.0904022977602015,
                    -1.0122048987516266,
                    -0.0002618904057581496,
                    -0.00026014827977743774,
                    0.0012454223653411514,
                    -0.005339411542581131,
                    -0.0010933714695477168,
                    -0.00003602409495541848,
                    -0.004907429898701641,
                    0.002407709550099145,
                    0.0070740067706853895,
                    0.007234509683753427,
                    -0.003747089044156331,
                    -0.0022270259657182837,
                    -0.0011816736261169667,
                    -0.001851744663647278,
                    0.000021321286550704532,
                    -0.0030348024768044523,
                    0.0008848474370985525,
                    0.00042133494512489,
                    0.0016757108272773794
                ],
                "feedback": [
                    0.9999990463256836,
                    0.9247647384931492
                ]
            },
            "output_mode": "direct"
        },
        "B4/flux": {
            "kind": "opx-output",
            "offset": 0.114743772754262,
            "filter": {
                "feedforward": [
                    1.0734385578459338,
                    -0.9226012969115566,
                    -0.0012001918315135262,
                    -0.0011812580080615897,
                    0.004708012004396109,
                    0.00038458072182711873,
                    -0.0027448062764590673,
                    -0.001510379655015391,
                    0.00043245097388778196,
                    -0.006387900990144783,
                    0.006796112075766038,
                    0.006114893325328795,
                    -0.002732990873425759,
                    0.000554036742509732,
                    -0.0015467483392273174,
                    -0.005864038922833063,
                    -0.002782663344249303,
                    0.0011379752751218527,
                    -0.0025231835161848943,
                    -0.011696060798588778,
                    0.014953813377825179
                ],
                "feedback": [
                    0.9999990463256836,
                    0.8510221712354766
                ]
            },
            "output_mode": "direct"
        },
        "B5/flux": {
            "kind": "opx-output",
            "offset": 0.0,
            "filter": {},
            "output_mode": "direct"
        },
        "D1/flux": {
            "kind": "opx-output",
            "offset": -0.4530870218982913,
            "filter": {
                "feedforward": [
                    1.1298143371682787,
                    -0.9007185757251136
                ],
                "feedback": [
                    0.7709042385568349
                ]
            },
            "output_mode": "direct"
        },
        "D2/flux": {
            "kind": "opx-output",
            "offset": -0.2224873138863394,
            "filter": {
                "feedforward": [
                    1.0891790415038731,
                    -1.024484298837039
                ],
                "feedback": [
                    0.935305257333166
                ]
            },
            "output_mode": "direct"
        },
        "D3/flux": {
            "kind": "opx-output",
            "offset": 0.05128942239382605,
            "filter": {
                "feedforward": [
                    1.1298143371682787,
                    -0.9007185757251136
                ],
                "feedback": [
                    0.7709042385568349
                ]
            },
            "output_mode": "direct"
        },
        "D4/flux": {
            "kind": "opx-output",
            "offset": -0.08416990010352905,
            "filter": {},
            "output_mode": "direct"
        },
        "D5/flux": {
            "kind": "opx-output",
            "offset": 0.05418914676504196,
            "filter": {},
            "output_mode": "direct"
        },
        "A1A4/drive_lo": {
            "kind": "octave-oscillator",
            "frequency": 4900000000.0,
            "power": 0.0,
            "output_mode": "triggered"
        },
        "A2A3/drive_lo": {
            "kind": "octave-oscillator",
            "frequency": 5700000000.0,
            "power": 0.0,
            "output_mode": "triggered"
        },
        "A5D5/drive_lo": {
            "kind": "octave-oscillator",
            "frequency": 5700000000.0,
            "power": 0.0,
            "output_mode": "triggered"
        },
        "A6D4/drive_lo": {
            "kind": "octave-oscillator",
            "frequency": 6400000000.0,
            "power": 0.0,
            "output_mode": "triggered"
        },
        "B1/drive_lo": {
            "kind": "octave-oscillator",
            "frequency": 4900000000.0,
            "power": 0.0,
            "output_mode": "triggered"
        },
        "B2/drive_lo": {
            "kind": "octave-oscillator",
            "frequency": 5900000000.0,
            "power": 0.0,
            "output_mode": "triggered"
        },
        "B3/drive_lo": {
            "kind": "octave-oscillator",
            "frequency": 5800000000.0,
            "power": 0.0,
            "output_mode": "triggered"
        },
        "B4/drive_lo": {
            "kind": "octave-oscillator",
            "frequency": 6700000000.0,
            "power": 0.0,
            "output_mode": "triggered"
        },
        "B5/drive_lo": {
            "kind": "octave-oscillator",
            "frequency": 5900000000.0,
            "power": 0.0,
            "output_mode": "triggered"
        },
        "D1/drive_lo": {
            "kind": "octave-oscillator",
            "frequency": 5100000000.0,
            "power": 0.0,
            "output_mode": "triggered"
        },
        "D2D3/drive_lo": {
            "kind": "octave-oscillator",
            "frequency": 5700000000.0,
            "power": 0.0,
            "output_mode": "triggered"
        },
        "A/probe_lo": {
            "kind": "octave-oscillator",
            "frequency": 7520000000.0,
            "power": 0.0,
            "output_mode": "triggered"
        },
        "B/probe_lo": {
            "kind": "octave-oscillator",
            "frequency": 7370000000.0,
            "power": -10.0,
            "output_mode": "triggered"
        },
        "D/probe_lo": {
            "kind": "octave-oscillator",
            "frequency": 7450000000.0,
            "power": 0.0,
            "output_mode": "triggered"
        }
    },
    "native_gates": {
        "single_qubit": {
            "A1": {
                "RX": [
                    [
                        "A1/drive",
                        {
                            "kind": "pulse",
                            "duration": 40.0,
                            "amplitude": 0.1,
                            "envelope": {
                                "kind": "gaussian",
                                "rel_sigma": 0.2
                            },
                            "relative_phase": 0.0
                        }
                    ]
                ],
                "RX90": null,
                "RX12": [
                    [
                        "A1/drive",
                        {
                            "kind": "pulse",
                            "duration": 40.0,
                            "amplitude": 0.1,
                            "envelope": {
                                "kind": "gaussian",
                                "rel_sigma": 0.2
                            },
                            "relative_phase": 0.0
                        }
                    ]
                ],
                "MZ": [
                    [
                        "A1/acquisition",
                        {
                            "kind": "readout",
                            "acquisition": {
                                "kind": "acquisition",
                                "duration": 2000.0
                            },
                            "probe": {
                                "kind": "pulse",
                                "duration": 2000.0,
                                "amplitude": 0.004,
                                "envelope": {
                                    "kind": "rectangular"
                                },
                                "relative_phase": 0.0
                            }
                        }
                    ]
                ],
                "CP": null
            },
            "A2": {
                "RX": [
                    [
                        "A2/drive",
                        {
                            "kind": "pulse",
                            "duration": 40.0,
                            "amplitude": 0.1,
                            "envelope": {
                                "kind": "gaussian",
                                "rel_sigma": 0.2
                            },
                            "relative_phase": 0.0
                        }
                    ]
                ],
                "RX90": null,
                "RX12": [
                    [
                        "A2/drive",
                        {
                            "kind": "pulse",
                            "duration": 40.0,
                            "amplitude": 0.1,
                            "envelope": {
                                "kind": "gaussian",
                                "rel_sigma": 0.2
                            },
                            "relative_phase": 0.0
                        }
                    ]
                ],
                "MZ": [
                    [
                        "A2/acquisition",
                        {
                            "kind": "readout",
                            "acquisition": {
                                "kind": "acquisition",
                                "duration": 2000.0
                            },
                            "probe": {
                                "kind": "pulse",
                                "duration": 2000.0,
                                "amplitude": 0.004,
                                "envelope": {
                                    "kind": "rectangular"
                                },
                                "relative_phase": 0.0
                            }
                        }
                    ]
                ],
                "CP": null
            },
            "A3": {
                "RX": [
                    [
                        "A3/drive",
                        {
                            "kind": "pulse",
                            "duration": 40.0,
                            "amplitude": 0.1,
                            "envelope": {
                                "kind": "gaussian",
                                "rel_sigma": 0.2
                            },
                            "relative_phase": 0.0
                        }
                    ]
                ],
                "RX90": null,
                "RX12": [
                    [
                        "A3/drive",
                        {
                            "kind": "pulse",
                            "duration": 40.0,
                            "amplitude": 0.1,
                            "envelope": {
                                "kind": "gaussian",
                                "rel_sigma": 0.2
                            },
                            "relative_phase": 0.0
                        }
                    ]
                ],
                "MZ": [
                    [
                        "A3/acquisition",
                        {
                            "kind": "readout",
                            "acquisition": {
                                "kind": "acquisition",
                                "duration": 2000.0
                            },
                            "probe": {
                                "kind": "pulse",
                                "duration": 2000.0,
                                "amplitude": 0.004,
                                "envelope": {
                                    "kind": "rectangular"
                                },
                                "relative_phase": 0.0
                            }
                        }
                    ]
                ],
                "CP": null
            },
            "A4": {
                "RX": [
                    [
                        "A4/drive",
                        {
                            "kind": "pulse",
                            "duration": 40.0,
                            "amplitude": 0.1,
                            "envelope": {
                                "kind": "gaussian",
                                "rel_sigma": 0.2
                            },
                            "relative_phase": 0.0
                        }
                    ]
                ],
                "RX90": null,
                "RX12": [
                    [
                        "A4/drive",
                        {
                            "kind": "pulse",
                            "duration": 40.0,
                            "amplitude": 0.1,
                            "envelope": {
                                "kind": "gaussian",
                                "rel_sigma": 0.2
                            },
                            "relative_phase": 0.0
                        }
                    ]
                ],
                "MZ": [
                    [
                        "A4/acquisition",
                        {
                            "kind": "readout",
                            "acquisition": {
                                "kind": "acquisition",
                                "duration": 2000.0
                            },
                            "probe": {
                                "kind": "pulse",
                                "duration": 2000.0,
                                "amplitude": 0.004,
                                "envelope": {
                                    "kind": "rectangular"
                                },
                                "relative_phase": 0.0
                            }
                        }
                    ]
                ],
                "CP": null
            },
            "A5": {
                "RX": [
                    [
                        "A5/drive",
                        {
                            "kind": "pulse",
                            "duration": 40.0,
                            "amplitude": 0.1,
                            "envelope": {
                                "kind": "gaussian",
                                "rel_sigma": 0.2
                            },
                            "relative_phase": 0.0
                        }
                    ]
                ],
                "RX90": null,
                "RX12": [
                    [
                        "A5/drive",
                        {
                            "kind": "pulse",
                            "duration": 40.0,
                            "amplitude": 0.1,
                            "envelope": {
                                "kind": "gaussian",
                                "rel_sigma": 0.2
                            },
                            "relative_phase": 0.0
                        }
                    ]
                ],
                "MZ": [
                    [
                        "A5/acquisition",
                        {
                            "kind": "readout",
                            "acquisition": {
                                "kind": "acquisition",
                                "duration": 2000.0
                            },
                            "probe": {
                                "kind": "pulse",
                                "duration": 2000.0,
                                "amplitude": 0.004,
                                "envelope": {
                                    "kind": "rectangular"
                                },
                                "relative_phase": 0.0
                            }
                        }
                    ]
                ],
                "CP": null
            },
            "A6": {
                "RX": [
                    [
                        "A6/drive",
                        {
                            "kind": "pulse",
                            "duration": 40.0,
                            "amplitude": 0.1,
                            "envelope": {
                                "kind": "gaussian",
                                "rel_sigma": 0.2
                            },
                            "relative_phase": 0.0
                        }
                    ]
                ],
                "RX90": null,
                "RX12": [
                    [
                        "A6/drive",
                        {
                            "kind": "pulse",
                            "duration": 40.0,
                            "amplitude": 0.1,
                            "envelope": {
                                "kind": "gaussian",
                                "rel_sigma": 0.2
                            },
                            "relative_phase": 0.0
                        }
                    ]
                ],
                "MZ": [
                    [
                        "A6/acquisition",
                        {
                            "kind": "readout",
                            "acquisition": {
                                "kind": "acquisition",
                                "duration": 2000.0
                            },
                            "probe": {
                                "kind": "pulse",
                                "duration": 2000.0,
                                "amplitude": 0.004,
                                "envelope": {
                                    "kind": "rectangular"
                                },
                                "relative_phase": 0.0
                            }
                        }
                    ]
                ],
                "CP": null
            },
            "B1": {
                "RX": [
                    [
                        "B1/drive",
                        {
                            "kind": "pulse",
                            "duration": 40.0,
                            "amplitude": 0.08723350760636656,
                            "envelope": {
                                "kind": "drag",
                                "rel_sigma": 0.2,
                                "beta": 0.65
                            },
                            "relative_phase": 0.0
                        }
                    ]
                ],
                "RX90": null,
                "RX12": [
                    [
                        "B1/drive",
                        {
                            "kind": "pulse",
                            "duration": 40.0,
                            "amplitude": 0.1,
                            "envelope": {
                                "kind": "gaussian",
                                "rel_sigma": 0.2
                            },
                            "relative_phase": 0.0
                        }
                    ]
                ],
                "MZ": [
                    [
                        "B1/acquisition",
                        {
                            "kind": "readout",
                            "acquisition": {
                                "kind": "acquisition",
                                "duration": 2000.0
                            },
                            "probe": {
                                "kind": "pulse",
                                "duration": 2000.0,
                                "amplitude": 0.0062,
                                "envelope": {
                                    "kind": "rectangular"
                                },
                                "relative_phase": 0.0
                            }
                        }
                    ]
                ],
                "CP": null
            },
            "B2": {
                "RX": [
                    [
                        "B2/drive",
                        {
                            "kind": "pulse",
                            "duration": 40.0,
                            "amplitude": 0.09747383943677225,
                            "envelope": {
                                "kind": "drag",
                                "rel_sigma": 0.2,
                                "beta": -0.485437
                            },
                            "relative_phase": 0.0
                        }
                    ]
                ],
                "RX90": null,
                "RX12": [
                    [
                        "B2/drive",
                        {
                            "kind": "pulse",
                            "duration": 40.0,
                            "amplitude": 0.102,
                            "envelope": {
                                "kind": "gaussian",
                                "rel_sigma": 0.2
                            },
                            "relative_phase": 0.0
                        }
                    ]
                ],
                "MZ": [
                    [
                        "B2/acquisition",
                        {
                            "kind": "readout",
                            "acquisition": {
                                "kind": "acquisition",
                                "duration": 2000.0
                            },
                            "probe": {
                                "kind": "pulse",
                                "duration": 2000.0,
                                "amplitude": 0.0042,
                                "envelope": {
                                    "kind": "rectangular"
                                },
                                "relative_phase": 0.0
                            }
                        }
                    ]
                ],
                "CP": null
            },
            "B3": {
                "RX": [
                    [
                        "B3/drive",
                        {
                            "kind": "pulse",
                            "duration": 40.0,
                            "amplitude": 0.12803113613901518,
                            "envelope": {
                                "kind": "drag",
                                "rel_sigma": 0.2,
                                "beta": -0.603462
                            },
                            "relative_phase": 0.0
                        }
                    ]
                ],
                "RX90": null,
                "RX12": [
                    [
                        "B3/drive",
                        {
                            "kind": "pulse",
                            "duration": 40.0,
                            "amplitude": 0.1,
                            "envelope": {
                                "kind": "gaussian",
                                "rel_sigma": 0.2
                            },
                            "relative_phase": 0.0
                        }
                    ]
                ],
                "MZ": [
                    [
                        "B3/acquisition",
                        {
                            "kind": "readout",
                            "acquisition": {
                                "kind": "acquisition",
                                "duration": 2000.0
                            },
                            "probe": {
                                "kind": "pulse",
                                "duration": 2000.0,
                                "amplitude": 0.0034,
                                "envelope": {
                                    "kind": "rectangular"
                                },
                                "relative_phase": 0.0
                            }
                        }
                    ]
                ],
                "CP": null
            },
            "B4": {
                "RX": [
                    [
                        "B4/drive",
                        {
                            "kind": "pulse",
                            "duration": 40.0,
                            "amplitude": 0.1492319934760541,
                            "envelope": {
                                "kind": "drag",
                                "rel_sigma": 0.2,
                                "beta": -0.556924
                            },
                            "relative_phase": 0.0
                        }
                    ]
                ],
                "RX90": null,
                "RX12": [
                    [
                        "B4/drive",
                        {
                            "kind": "pulse",
                            "duration": 40.0,
                            "amplitude": 0.1,
                            "envelope": {
                                "kind": "gaussian",
                                "rel_sigma": 0.2
                            },
                            "relative_phase": 0.0
                        }
                    ]
                ],
                "MZ": [
                    [
                        "B4/acquisition",
                        {
                            "kind": "readout",
                            "acquisition": {
                                "kind": "acquisition",
                                "duration": 2000.0
                            },
                            "probe": {
                                "kind": "pulse",
                                "duration": 2000.0,
                                "amplitude": 0.0066,
                                "envelope": {
                                    "kind": "rectangular"
                                },
                                "relative_phase": 0.0
                            }
                        }
                    ]
                ],
                "CP": null
            },
            "B5": {
                "RX": [
                    [
                        "B5/drive",
                        {
                            "kind": "pulse",
                            "duration": 40.0,
                            "amplitude": 0.12524318098993786,
                            "envelope": {
                                "kind": "drag",
                                "rel_sigma": 0.2,
                                "beta": -0.15
                            },
                            "relative_phase": 0.0
                        }
                    ]
                ],
                "RX90": null,
                "RX12": [
                    [
                        "B5/drive",
                        {
                            "kind": "pulse",
                            "duration": 40.0,
                            "amplitude": 0.1,
                            "envelope": {
                                "kind": "gaussian",
                                "rel_sigma": 0.2
                            },
                            "relative_phase": 0.0
                        }
                    ]
                ],
                "MZ": [
                    [
                        "B5/acquisition",
                        {
                            "kind": "readout",
                            "acquisition": {
                                "kind": "acquisition",
                                "duration": 2000.0
                            },
                            "probe": {
                                "kind": "pulse",
                                "duration": 2000.0,
                                "amplitude": 0.007,
                                "envelope": {
                                    "kind": "rectangular"
                                },
                                "relative_phase": 0.0
                            }
                        }
                    ]
                ],
                "CP": null
            },
            "D1": {
                "RX": [
                    [
                        "D1/drive",
                        {
                            "kind": "pulse",
                            "duration": 40.0,
                            "amplitude": 0.0826507236496066,
                            "envelope": {
                                "kind": "gaussian",
                                "rel_sigma": 0.2
                            },
                            "relative_phase": 0.0
                        }
                    ]
                ],
                "RX90": null,
                "RX12": [
                    [
                        "D1/drive",
                        {
                            "kind": "pulse",
                            "duration": 40.0,
                            "amplitude": 0.1,
                            "envelope": {
                                "kind": "gaussian",
                                "rel_sigma": 0.2
                            },
                            "relative_phase": 0.0
                        }
                    ]
                ],
                "MZ": [
                    [
                        "D1/acquisition",
                        {
                            "kind": "readout",
                            "acquisition": {
                                "kind": "acquisition",
                                "duration": 1000.0
                            },
                            "probe": {
                                "kind": "pulse",
                                "duration": 1000.0,
                                "amplitude": 0.004,
                                "envelope": {
                                    "kind": "rectangular"
                                },
                                "relative_phase": 0.0
                            }
                        }
                    ]
                ],
                "CP": null
            },
            "D2": {
                "RX": [
                    [
                        "D2/drive",
                        {
                            "kind": "pulse",
                            "duration": 40.0,
                            "amplitude": 0.1063918599542511,
                            "envelope": {
                                "kind": "gaussian",
                                "rel_sigma": 0.2
                            },
                            "relative_phase": 0.0
                        }
                    ]
                ],
                "RX90": null,
                "RX12": [
                    [
                        "D2/drive",
                        {
                            "kind": "pulse",
                            "duration": 40.0,
                            "amplitude": 0.1,
                            "envelope": {
                                "kind": "gaussian",
                                "rel_sigma": 0.2
                            },
                            "relative_phase": 0.0
                        }
                    ]
                ],
                "MZ": [
                    [
                        "D2/acquisition",
                        {
                            "kind": "readout",
                            "acquisition": {
                                "kind": "acquisition",
                                "duration": 1000.0
                            },
                            "probe": {
                                "kind": "pulse",
                                "duration": 1000.0,
                                "amplitude": 0.006,
                                "envelope": {
                                    "kind": "rectangular"
                                },
                                "relative_phase": 0.0
                            }
                        }
                    ]
                ],
                "CP": null
            },
            "D3": {
                "RX": [
                    [
                        "D3/drive",
                        {
                            "kind": "pulse",
                            "duration": 40.0,
                            "amplitude": 0.13610196612852987,
                            "envelope": {
                                "kind": "gaussian",
                                "rel_sigma": 0.2
                            },
                            "relative_phase": 0.0
                        }
                    ]
                ],
                "RX90": null,
                "RX12": [
                    [
                        "D3/drive",
                        {
                            "kind": "pulse",
                            "duration": 40.0,
                            "amplitude": 0.1,
                            "envelope": {
                                "kind": "gaussian",
                                "rel_sigma": 0.2
                            },
                            "relative_phase": 0.0
                        }
                    ]
                ],
                "MZ": [
                    [
                        "D3/acquisition",
                        {
                            "kind": "readout",
                            "acquisition": {
                                "kind": "acquisition",
                                "duration": 1000.0
                            },
                            "probe": {
                                "kind": "pulse",
                                "duration": 1000.0,
                                "amplitude": 0.005,
                                "envelope": {
                                    "kind": "rectangular"
                                },
                                "relative_phase": 0.0
                            }
                        }
                    ]
                ],
                "CP": null
            },
            "D4": {
                "RX": [
                    [
                        "D4/drive",
                        {
                            "kind": "pulse",
                            "duration": 40.0,
                            "amplitude": 0.15679611640490315,
                            "envelope": {
                                "kind": "gaussian",
                                "rel_sigma": 0.2
                            },
                            "relative_phase": 0.0
                        }
                    ]
                ],
                "RX90": null,
                "RX12": [
                    [
                        "D4/drive",
                        {
                            "kind": "pulse",
                            "duration": 40.0,
                            "amplitude": 0.1,
                            "envelope": {
                                "kind": "gaussian",
                                "rel_sigma": 0.2
                            },
                            "relative_phase": 0.0
                        }
                    ]
                ],
                "MZ": [
                    [
                        "D4/acquisition",
                        {
                            "kind": "readout",
                            "acquisition": {
                                "kind": "acquisition",
                                "duration": 2000.0
                            },
                            "probe": {
                                "kind": "pulse",
                                "duration": 2000.0,
                                "amplitude": 0.004,
                                "envelope": {
                                    "kind": "rectangular"
                                },
                                "relative_phase": 0.0
                            }
                        }
                    ]
                ],
                "CP": null
            },
            "D5": {
                "RX": [
                    [
                        "D5/drive",
                        {
                            "kind": "pulse",
                            "duration": 40.0,
                            "amplitude": 0.12066453809734043,
                            "envelope": {
                                "kind": "gaussian",
                                "rel_sigma": 0.2
                            },
                            "relative_phase": 0.0
                        }
                    ]
                ],
                "RX90": null,
                "RX12": [
                    [
                        "D5/drive",
                        {
                            "kind": "pulse",
                            "duration": 40.0,
                            "amplitude": 0.1,
                            "envelope": {
                                "kind": "gaussian",
                                "rel_sigma": 0.2
                            },
                            "relative_phase": 0.0
                        }
                    ]
                ],
                "MZ": [
                    [
                        "D5/acquisition",
                        {
                            "kind": "readout",
                            "acquisition": {
                                "kind": "acquisition",
                                "duration": 2000.0
                            },
                            "probe": {
                                "kind": "pulse",
                                "duration": 2000.0,
                                "amplitude": 0.0036,
                                "envelope": {
                                    "kind": "rectangular"
                                },
                                "relative_phase": 0.0
                            }
                        }
                    ]
                ],
                "CP": null
            }
        },
        "coupler": {},
        "two_qubit": {
            "B1-B2": {
                "CZ": [
                    [
                        "B2/flux",
                        {
                            "kind": "pulse",
                            "duration": 47.0,
                            "amplitude": -0.57536,
                            "envelope": {
                                "kind": "rectangular"
                            },
                            "relative_phase": 0.0
                        }
                    ],
                    [
                        "B1/drive",
                        {
                            "kind": "virtualz",
                            "phase": -0.06685245585620225
                        }
                    ],
                    [
                        "B2/drive",
                        {
                            "kind": "virtualz",
                            "phase": -1.9815486812412606
                        }
                    ]
                ],
                "CNOT": null,
                "iSWAP": null
            },
            "B1-B3": {
                "CZ": [
                    [
                        "B3/flux",
                        {
                            "kind": "pulse",
                            "duration": 38.0,
                            "amplitude": 0.4346999999999995,
                            "envelope": {
                                "kind": "rectangular"
                            },
                            "relative_phase": 0.0
                        }
                    ],
                    [
                        "B1/drive",
                        {
                            "kind": "virtualz",
                            "phase": -0.07662830332580176
                        }
                    ],
                    [
                        "B3/drive",
                        {
                            "kind": "virtualz",
                            "phase": -0.43444539289217665
                        }
                    ]
                ],
                "CNOT": null,
                "iSWAP": null
            },
            "B2-B4": {
                "CZ": [
                    [
                        "B4/flux",
                        {
                            "kind": "pulse",
                            "duration": 33.0,
                            "amplitude": -0.4776,
                            "envelope": {
                                "kind": "rectangular"
                            },
                            "relative_phase": 0.0
                        }
                    ],
                    [
                        "B2/drive",
                        {
                            "kind": "virtualz",
                            "phase": 0.0
                        }
                    ],
                    [
                        "B4/drive",
                        {
                            "kind": "virtualz",
                            "phase": 0.0
                        }
                    ]
                ],
                "CNOT": null,
                "iSWAP": null
            },
            "B3-B4": {
                "CZ": [
                    [
                        "B4/flux",
                        {
                            "kind": "pulse",
                            "duration": 38.0,
                            "amplitude": 0.57,
                            "envelope": {
                                "kind": "rectangular"
                            },
                            "relative_phase": 0.0
                        }
                    ],
                    [
                        "B3/drive",
                        {
                            "kind": "virtualz",
                            "phase": 0.0
                        }
                    ],
                    [
                        "B4/drive",
                        {
                            "kind": "virtualz",
                            "phase": 0.0
                        }
                    ]
                ],
                "CNOT": null,
                "iSWAP": null
            },
            "D1-D2": {
                "CZ": [
                    [
                        "D2/flux",
                        {
                            "kind": "pulse",
                            "duration": 48.0,
                            "amplitude": -0.4058,
                            "envelope": {
                                "kind": "rectangular"
                            },
                            "relative_phase": 0.0
                        }
                    ],
                    [
                        "D2/drive",
                        {
                            "kind": "virtualz",
                            "phase": -3.8045406837259605
                        }
                    ],
                    [
                        "D1/drive",
                        {
                            "kind": "virtualz",
                            "phase": -6.149457297781321
                        }
                    ]
                ],
                "CNOT": null,
                "iSWAP": [
                    [
                        "D2/flux",
                        {
                            "kind": "pulse",
                            "duration": 80.0,
                            "amplitude": 0.5,
                            "envelope": {
                                "kind": "rectangular"
                            },
                            "relative_phase": 0.0
                        }
                    ],
                    [
                        "D1/drive",
                        {
                            "kind": "virtualz",
                            "phase": 0.0
                        }
                    ],
                    [
                        "D2/drive",
                        {
                            "kind": "virtualz",
                            "phase": 0.0
                        }
                    ]
                ]
            },
            "D1-D3": {
                "CZ": [
                    [
                        "D3/flux",
                        {
                            "kind": "pulse",
                            "duration": 49.0,
                            "amplitude": 0.4606,
                            "envelope": {
                                "kind": "rectangular"
                            },
                            "relative_phase": 0.0
                        }
                    ],
                    [
                        "D1/drive",
                        {
                            "kind": "virtualz",
                            "phase": -6.204513832205662
                        }
                    ],
                    [
                        "D3/drive",
                        {
                            "kind": "virtualz",
                            "phase": -3.7793879059598057
                        }
                    ]
                ],
                "CNOT": null,
                "iSWAP": [
                    [
                        "D2/flux",
                        {
                            "kind": "pulse",
                            "duration": 80.0,
                            "amplitude": 0.5,
                            "envelope": {
                                "kind": "rectangular"
                            },
                            "relative_phase": 0.0
                        }
                    ],
                    [
                        "D1/drive",
                        {
                            "kind": "virtualz",
                            "phase": 0.0
                        }
                    ],
                    [
                        "D3/drive",
                        {
                            "kind": "virtualz",
                            "phase": 0.0
                        }
                    ]
                ]
            },
            "D2-D4": {
                "CZ": [
                    [
                        "D4/flux",
                        {
                            "kind": "pulse",
                            "duration": 70.0,
                            "amplitude": 0.4268,
                            "envelope": {
                                "kind": "rectangular"
                            },
                            "relative_phase": 0.0
                        }
                    ],
                    [
                        "D2/drive",
                        {
                            "kind": "virtualz",
                            "phase": -0.016968392949063747
                        }
                    ],
                    [
                        "D4/drive",
                        {
                            "kind": "virtualz",
                            "phase": -5.663817468134775
                        }
                    ]
                ],
                "CNOT": null,
                "iSWAP": [
                    [
                        "D2/flux",
                        {
                            "kind": "pulse",
                            "duration": 80.0,
                            "amplitude": 0.5,
                            "envelope": {
                                "kind": "rectangular"
                            },
                            "relative_phase": 0.0
                        }
                    ],
                    [
                        "D1/drive",
                        {
                            "kind": "virtualz",
                            "phase": 0.0
                        }
                    ],
                    [
                        "D2/drive",
                        {
                            "kind": "virtualz",
                            "phase": 0.0
                        }
                    ]
                ]
            }
        }
    }
}